{
  "id": "1476583",
  "name": "explorer",
  "font_family": "iconfont",
  "css_prefix_text": "icon-",
  "description": "",
  "glyphs": [
    {
      "icon_id": "5127397",
      "name": "list-alt",
      "font_class": "wl-list",
      "unicode": "e7be",
      "unicode_decimal": 59326
    },
    {
      "icon_id": "5327610",
      "name": "箭头-上",
      "font_class": "wl-up",
      "unicode": "e729",
      "unicode_decimal": 59177
    },
    {
      "icon_id": "5327617",
      "name": "箭头-下",
      "font_class": "wl-down",
      "unicode": "e72c",
      "unicode_decimal": 59180
    },
    {
      "icon_id": "5327619",
      "name": "箭头-右",
      "font_class": "wl-right",
      "unicode": "e72d",
      "unicode_decimal": 59181
    },
    {
      "icon_id": "5327620",
      "name": "箭头-左",
      "font_class": "wl-left",
      "unicode": "e72e",
      "unicode_decimal": 59182
    },
    {
      "icon_id": "6027503",
      "name": "右箭头",
      "font_class": "wl-right-round",
      "unicode": "e608",
      "unicode_decimal": 58888
    },
    {
      "icon_id": "6027505",
      "name": "左箭头",
      "font_class": "wl-left-round",
      "unicode": "e609",
      "unicode_decimal": 58889
    },
    {
      "icon_id": "7141412",
      "name": "grid-outline",
      "font_class": "wl-grid",
      "unicode": "e610",
      "unicode_decimal": 58896
    }
  ]
}
